simple_queue/__init__.py
simple_queue/exceptions.py
simple_queue/message.py
simple_queue/processor.py
simple_queue/queue.py
simple_queue/utils.py
simple_queue/worker.py
simple_queue-1.0.10.dist-info/METADATA
simple_queue-1.0.10.dist-info/WHEEL
simple_queue-1.0.10.dist-info/top_level.txt
simple_queue-1.0.10.dist-info/RECORD
